borisat/__init__.py
borisat/apis/__init__.py
borisat/apis/rd.py
borisat/models/__init__.py
borisat/models/rd/__init__.py
borisat/models/rd/unnested.py
borisat/models/rd/vat.py
borisat-1.0.0.dist-info/LICENSE
borisat-1.0.0.dist-info/WHEEL
borisat-1.0.0.dist-info/METADATA
borisat-1.0.0.dist-info/RECORD
