Metadata-Version: 2.1
Name: borisat
Version: 1.0.0
Summary: a python library for retrieving company public data in thailand. It has its own public database for caching, so, it is really fast, smart, and save lot of time and energy.
Home-page: https://github.com/CircleOnCircles/borisat
License: ISC
Author: Nutchanon Ninyawee
Author-email: nutchanon@codustry.com
Requires-Python: >=3.8,<4.0
Classifier: License :: OSI Approved
Classifier: Programming Language :: Python :: 3
Classifier: Programming Language :: Python :: 3.8
Classifier: Programming Language :: Python :: 3.9
Requires-Dist: loguru (>=0.5.3,<0.6.0)
Requires-Dist: pydantic (>=1.6.1,<2.0.0)
Requires-Dist: stringcase (>=1.2.0,<2.0.0)
Requires-Dist: zeep (>=3.4.0,<4.0.0)
Project-URL: Repository, https://github.com/CircleOnCircles/borisat
